planetmagfields/__init__.py
planetmagfields/libbfield.py
planetmagfields/libdata.py
planetmagfields/libgauss.py
planetmagfields/planet.py
planetmagfields/plotlib.py
planetmagfields/potextra.py
planetmagfields/utils.py
planetmagfields/data/earth_igrf14.dat
planetmagfields/data/ganymede_kivelson2002.dat
planetmagfields/data/jupiter_jrm09.dat
planetmagfields/data/jupiter_jrm33.dat
planetmagfields/data/jupiter_vip4.dat
planetmagfields/data/mercury_anderson2012.dat
planetmagfields/data/mercury_thebault2018.dat
planetmagfields/data/mercury_wardinski2019.dat
planetmagfields/data/neptune_connerny1991.dat
planetmagfields/data/neptune_holme1996.dat
planetmagfields/data/saturn_cassini11+.dat
planetmagfields/data/saturn_cassini11.dat
planetmagfields/data/saturn_cassinisoi.dat
planetmagfields/data/uranus_connerny1987.dat
planetmagfields/data/uranus_herbert2009.dat
planetmagfields/data/uranus_holme1996.dat
planetmagfields-1.5.8.dist-info/licenses/LICENSE
planetmagfields-1.5.8.dist-info/METADATA
planetmagfields-1.5.8.dist-info/WHEEL
planetmagfields-1.5.8.dist-info/top_level.txt
planetmagfields-1.5.8.dist-info/RECORD
