Metadata-Version: 2.4
Name: planetMagFields
Version: 1.5.8
Summary: Routines to easily access information about magnetic fields of planets in our solar system and visualize them in both 2D and 3D
Author: Barik, Ankit
Author-email: Ankit Barik <ankit.barik@gmail.com>
Maintainer-email: Ankit Barik <ankit.barik@gmail.com>, Regupathi Angappan <rangapp1@jhu.edu>
Project-URL: Homepage, https://ankitbarik.github.io/planetMagFields/
Project-URL: Issues, https://github.com/AnkitBarik/planetMagFields/issues
Keywords: Spherical Harmonics,Planetary Science,Spectra,Magnetic Field,Visualization,3D visualization
Classifier: Development Status :: 5 - Production/Stable
Classifier: Environment :: Console
Classifier: Programming Language :: Python :: 3
Classifier: License :: OSI Approved :: GNU General Public License v3 or later (GPLv3+)
Classifier: Operating System :: OS Independent
Classifier: Intended Audience :: Science/Research
Classifier: Intended Audience :: Education
Classifier: Intended Audience :: Developers
Classifier: Topic :: Scientific/Engineering
Classifier: Topic :: Scientific/Engineering :: Mathematics
Classifier: Topic :: Scientific/Engineering :: Physics
Classifier: Topic :: Scientific/Engineering :: Visualization
Requires-Python: >=3.7
License-File: LICENSE
Requires-Dist: numpy
Requires-Dist: scipy
Requires-Dist: matplotlib
Provides-Extra: map
Requires-Dist: cartopy; extra == "map"
Provides-Extra: potextra
Requires-Dist: shtns; extra == "potextra"
Provides-Extra: vtk
Requires-Dist: pyevtk; extra == "vtk"
Provides-Extra: all
Requires-Dist: planetMagFields[map,potextra,vtk]; extra == "all"
Dynamic: author
Dynamic: license-file
